overcome/__init__.py
overcome/analysis.py
overcome/overcome.py
overcome/calculator/__init__.py
overcome/calculator/outcomeprofits.py
overcome/minimizer/__init__.py
overcome/minimizer/costminimizer.py
overcome/minimizer/invalidminimization.py
overcome/minimizer/regularcostminimizer.py
overcome/position/__init__.py
overcome/position/evaluation.py
overcome/position/positions.py
overcome/stack/__init__.py
overcome/stack/measuredstack.py
overcome/stack/stack.py
overcome-0.6.0.dist-info/LICENSE.txt
overcome-0.6.0.dist-info/METADATA
overcome-0.6.0.dist-info/WHEEL
overcome-0.6.0.dist-info/top_level.txt
overcome-0.6.0.dist-info/RECORD
