Metadata-Version: 2.1
Name: overcome
Version: 0.6.0
Summary: Overcome is a data transformer to calculate the potential buying and selling earnings from the "high", "low" and "close" trading history values. Additional post operation analysis is provided.
Home-page: https://github.com/westial/overcome
Author: Jaume Mila Bea
Author-email: jaume@westial.com
Project-URL: Bug Tracker, https://github.com/westial/overcome/issues
Classifier: Programming Language :: Python :: 3
Classifier: License :: OSI Approved :: GNU General Public License v3 (GPLv3)
Classifier: Operating System :: OS Independent
Requires-Python: >=3.9.0
License-File: LICENSE.txt
Requires-Dist: numpy
Requires-Dist: pandas
Provides-Extra: dev
Requires-Dist: behave ; extra == 'dev'
